policy_tool/__init__.py
policy_tool/main.py
policy_tool/core/__init__.py
policy_tool/core/policy_assignment_types.py
policy_tool/core/snowflake_connection_setup.py
policy_tool/services/__init__.py
policy_tool/services/azure_devops_service.py
policy_tool/services/policy_assignment_comparison_service.py
policy_tool/services/policy_configuration_service.py
policy_tool/services/policy_metadata_service.py
policy_tool/services/policy_solution_service.py
policy_tool/services/policy_validation_service.py
policy_tool/services/snowflake_service.py
policy_tool/utils/__init__.py
policy_tool/utils/file_utils.py
policy_tool/utils/logger_utils.py
policy_tool/utils/parallelization_util.py
resources/json-schemas/configs/configs.schema.json
resources/json-schemas/policy_assignments/column_masking_policies.schema.json
resources/json-schemas/policy_assignments/policy_assignments.schema.json
resources/json-schemas/policy_assignments/row_access_policies.schema.json
tests/__init__.py
tests/policy_tool/services/policy_metadata_service_test.py
tests/policy_tool/services/policy_solution_service_test.py
tests/policy_tool/services/policy_validation_service_test.py
cloe_extensions_snowflake_policies-20250324.2.dist-info/METADATA
cloe_extensions_snowflake_policies-20250324.2.dist-info/WHEEL
cloe_extensions_snowflake_policies-20250324.2.dist-info/top_level.txt
cloe_extensions_snowflake_policies-20250324.2.dist-info/RECORD
