Metadata-Version: 2.1
Name: cloe-extensions-snowflake-policies
Version: 20250324.2
Summary: CMP and RAP policy framework for Snowflake DWH
Home-page: https://initions.com/
Author: initions
Author-email: ICSMC_EXT_PYPIORG@accenture.com
License: MIT
Requires-Dist: snowflake-connector-python (==3.1.0)
Requires-Dist: jsonschema (==4.18.4)
